db_loader/__init__.py
db_loader/migration.py
db_loader/mysql_connector/__init__.py
db_loader/mysql_connector/db_connector.py
db_loader/structs/__init__.py
db_loader/structs/migration.py
db_loader/structs/struct_strategy.py
db_loader/structs/structure.py
csv_db_loader-1.0.0.dist-info/METADATA
csv_db_loader-1.0.0.dist-info/WHEEL
csv_db_loader-1.0.0.dist-info/top_level.txt
csv_db_loader-1.0.0.dist-info/RECORD
