Metadata-Version: 2.1
Name: csv-db-loader
Version: 1.0.0
Summary: Python package that enables customized loading of data from a CSV file into a MySQL database
Author: Chavis
Author-email: chavis.delcourt@gmail.com
License: MIT
Keywords: python,csv,mysql,database,loader,db,load,csv_db_loader
Classifier: Development Status :: 1 - Planning
Classifier: Intended Audience :: Developers
Classifier: Programming Language :: Python :: 3
Classifier: Operating System :: Unix
Classifier: Operating System :: MacOS :: MacOS X
Classifier: Operating System :: Microsoft :: Windows
Requires-Dist: mysql-connector-python ==8.0.32
